ftbx/__init__.py
ftbx/autobuild_flex_version_schemas.py
ftbx/ftbx.py
ftbx/version.py
ftbx-1.2.3.dist-info/licenses/LICENSE
src/__init__.py
src/_consul.py
src/_database.py
src/_encryption.py
src/_environment.py
src/_objects.py
src/_rabbitmq.py
src/_session.py
src/utils.py
src/variables.py
src/cmd/__init__.py
src/cmd/assert_cmd.py
src/cmd/cancel_cmd.py
src/cmd/compare_cmd.py
src/cmd/connect_cmd.py
src/cmd/create_cmd.py
src/cmd/env_cmd.py
src/cmd/fail_cmd.py
src/cmd/init_cmd.py
src/cmd/launch_cmd.py
src/cmd/list_cmd.py
src/cmd/metadata_designer_cmd.py
src/cmd/pull_cmd.py
src/cmd/push_cmd.py
src/cmd/query_cmd.py
src/cmd/restore_cmd.py
src/cmd/retry_cmd.py
src/cmd/setup_cmd.py
src/cmd/update_cmd.py
src/cmd/workflow_designer_cmd.py
src/schemas/2021_10_x.py
src/schemas/2021_11_x.py
src/schemas/2021_12_x.py
src/schemas/2021_5_x.py
src/schemas/2021_8_x.py
src/schemas/2021_9_x.py
src/schemas/2022_11_x.py
src/schemas/2022_12_x.py
src/schemas/2022_3_x.py
src/schemas/2022_5_x.py
src/schemas/2022_7_x.py
src/schemas/2022_8_x.py
src/schemas/2022_9_x.py
src/schemas/2023_10_x.py
src/schemas/2023_11_x.py
src/schemas/2023_12_x.py
src/schemas/2023_2_x.py
src/schemas/2023_4_x.py
src/schemas/2023_6_x.py
src/schemas/2023_7_x.py
src/schemas/2023_8_x.py
src/schemas/2024_1_x.py
src/schemas/2024_3_x.py
src/schemas/2024_4_x.py
src/schemas/2024_5_x.py
src/schemas/2024_7_x.py
src/schemas/2024_8_x.py
src/schemas/2024_9_x.py
src/schemas/latest.py
ftbx-1.2.3.dist-info/METADATA
ftbx-1.2.3.dist-info/WHEEL
ftbx-1.2.3.dist-info/entry_points.txt
ftbx-1.2.3.dist-info/top_level.txt
ftbx-1.2.3.dist-info/RECORD
