Metadata-Version: 2.4
Name: ftbx
Version: 1.2.3
Summary: Tool to facilitate and accelerate Flex operations. 
Author: David NAISSE
Author-email: dnaisse@dalet.com
Maintainer: David NAISSE
Maintainer-email: dnaisse@dalet.com
License: Copyright 2024 Dalet Digital Media Systems, all rights reserved
Requires-Python: >=3.10
License-File: LICENSE
Requires-Dist: certifi==2024.8.30
Requires-Dist: cffi==1.17.1
Requires-Dist: charset-normalizer==3.4.0
Requires-Dist: click==8.1.7
Requires-Dist: cryptography==43.0.3
Requires-Dist: graphviz==0.20.3
Requires-Dist: idna==3.10
Requires-Dist: markdown-it-py==3.0.0
Requires-Dist: mdurl==0.1.2
Requires-Dist: mysql-connector-python==9.1.0
Requires-Dist: numpy==2.1.3
Requires-Dist: pandas==2.2.3
Requires-Dist: pika==1.3.2
Requires-Dist: pycparser==2.22
Requires-Dist: Pygments==2.18.0
Requires-Dist: python-consul==1.1.0
Requires-Dist: python-dateutil==2.9.0.post0
Requires-Dist: pytz==2024.2
Requires-Dist: requests==2.32.3
Requires-Dist: rich==13.9.4
Requires-Dist: shellingham==1.5.4
Requires-Dist: six==1.16.0
Requires-Dist: tqdm==4.67.0
Requires-Dist: typer==0.13.0
Requires-Dist: typing_extensions==4.12.2
Requires-Dist: tzdata==2024.2
Requires-Dist: urllib3==2.2.3
Dynamic: license-file
